dhis2_etl/__init__.py
dhis2_etl/admin.py
dhis2_etl/apps.py
dhis2_etl/urls.py
dhis2_etl/utils.py
dhis2_etl/views.py
dhis2_etl/builders/__init__.py
dhis2_etl/builders/dhis2/CategoryConverter.py
dhis2_etl/builders/dhis2/ClaimConverter.py
dhis2_etl/builders/dhis2/FundingConverter.py
dhis2_etl/builders/dhis2/InsureeConverter.py
dhis2_etl/builders/dhis2/LocationConverter.py
dhis2_etl/builders/dhis2/OptionSetConverter.py
dhis2_etl/builders/dhis2/__init__.py
dhis2_etl/configurations/__init__.py
dhis2_etl/configurations/generalConfiguration.py
dhis2_etl/configurations/moduleConfiguration.py
dhis2_etl/management/__init__.py
dhis2_etl/management/utiils.py
dhis2_etl/management/commands/__init__.py
dhis2_etl/management/commands/pushadx.py
dhis2_etl/management/commands/pushmetadata.py
dhis2_etl/management/commands/pushprogram.py
dhis2_etl/migrations/__init__.py
dhis2_etl/scheduled_tasks/__init__.py
dhis2_etl/scheduled_tasks/sync_function.py
dhis2_etl/scheduled_tasks/utils.py
dhis2_etl/serializers/__init__.py
dhis2_etl/services/__init__.py
dhis2_etl/services/adx_metadata.py
dhis2_etl/services/adx_service.py
dhis2_etl/services/claimServices.py
dhis2_etl/services/fundingServices.py
dhis2_etl/services/insureeServices.py
dhis2_etl/services/locationServices.py
dhis2_etl/services/optionSetServices.py
dhis2_etl/services/adx/__init__.py
dhis2_etl/services/adx/categories.py
dhis2_etl/services/adx/cubes.py
dhis2_etl/services/adx/data_values.py
dhis2_etl/services/adx/groups.py
dhis2_etl/services/adx/utils.py
dhis2_etl/strategy/__init__.py
dhis2_etl/strategy/adx_client.py
dhis2_etl/strategy/dhis2_client.py
dhis2_etl/tests/__init__.py
dhis2_etl/tests/adx_client_tests.py
dhis2_etl/tests/adx_tests.py
dhis2_etl/tests/daily_sync_tests.py
openimis_be_dhis2_etl-1.3.1.dist-info/LICENSE
openimis_be_dhis2_etl-1.3.1.dist-info/LICENSE.md
openimis_be_dhis2_etl-1.3.1.dist-info/METADATA
openimis_be_dhis2_etl-1.3.1.dist-info/WHEEL
openimis_be_dhis2_etl-1.3.1.dist-info/top_level.txt
openimis_be_dhis2_etl-1.3.1.dist-info/RECORD
