Metadata-Version: 2.1
Name: openimis-be-dhis2_etl
Version: 1.3.1
Summary: The openIMIS Backend to send data to DHIS2.
Home-page: https://openimis.org/
Author: Patrick Delcroix
Author-email: patrick.delcroix@swisstph.ch
License: GNU AGPL v3
Classifier: Environment :: Web Environment
Classifier: Framework :: Django
Classifier: Framework :: Django :: 3.1
Classifier: Intended Audience :: Developers
Classifier: License :: OSI Approved :: GNU Affero General Public License v3
Classifier: Operating System :: OS Independent
Classifier: Programming Language :: Python
Classifier: Programming Language :: Python :: 3.7
Classifier: Programming Language :: Python :: 3.8
Classifier: Programming Language :: Python :: 3.9
Classifier: Programming Language :: Python :: 3.10
License-File: LICENSE
License-File: LICENSE.md
Requires-Dist: django
Requires-Dist: django-db-signals
Requires-Dist: django-adx
Requires-Dist: email-validator
Requires-Dist: dict2obj
